safrac/__init__.py
safrac/generator.py
safrac/mask.py
safrac-21.3.17.dist-info/LICENSE.txt
safrac-21.3.17.dist-info/METADATA
safrac-21.3.17.dist-info/WHEEL
safrac-21.3.17.dist-info/pbr.json
safrac-21.3.17.dist-info/top_level.txt
safrac-21.3.17.dist-info/RECORD
