Metadata-Version: 2.1
Name: safrac
Version: 21.3.17
Summary: This is a fractal generator for geophysical models.
Home-page: https://github.com/cstatz/safrac
Author: Christoph Statz
Author-email: christoph.statz@tu-dresden.de
License: UNKNOWN
Platform: UNKNOWN
Classifier: Programming Language :: Python :: 3
Classifier: Environment :: Console
Classifier: Intended Audience :: Developers
Classifier: Intended Audience :: Science/Research
Classifier: License :: OSI Approved :: BSD License
Classifier: Operating System :: OS Independent
Classifier: Topic :: Scientific/Engineering :: Physics
Classifier: Natural Language :: English
Requires-Python: >=3.6
Requires-Dist: numpy (>=1.18.0)
Requires-Dist: numba (>=0.51.0)
